./.gitignore
./PKG-INFO
./QUICKSTART.md
./README.md
./config.py
./env.example
./main.py
./mcp.txt
./py_SDK.txt
./pyproject.toml
./requirements.txt
./run.py
./test_speech_to_text.py
./uv.lock
iflow_mcp_dw_mcp_server-0.1.0.dist-info/METADATA
iflow_mcp_dw_mcp_server-0.1.0.dist-info/WHEEL
iflow_mcp_dw_mcp_server-0.1.0.dist-info/entry_points.txt
iflow_mcp_dw_mcp_server-0.1.0.dist-info/RECORD
