Metadata-Version: 2.4
Name: iflow-mcp_dw-mcp-server
Version: 0.1.0
Summary: 语音转文字 MCP 服务器 - 支持多种音频格式和识别引擎
Requires-Python: >=3.13
Requires-Dist: mcp[cli]>=1.11.0
Requires-Dist: pydantic>=2.0.0
Requires-Dist: pydub>=0.25.1
Requires-Dist: requests>=2.31.0
Requires-Dist: speechrecognition>=3.10.0
Requires-Dist: uvicorn>=0.24.0
Provides-Extra: dev
Requires-Dist: black>=23.0.0; extra == 'dev'
Requires-Dist: isort>=5.12.0; extra == 'dev'
Requires-Dist: mypy>=1.0.0; extra == 'dev'
Requires-Dist: pytest-asyncio>=0.21.0; extra == 'dev'
Requires-Dist: pytest>=7.0.0; extra == 'dev'
